{
    "truePoint": [
        {
            "point": [
                {
                    "x": 90.56,
                    "y": 361
                },
                {
                    "x": 140.56,
                    "y": 411
                }
            ]
        },
        {
            "point": [
                {
                    "x": 112.78,
                    "y": 337
                },
                {
                    "x": 162.78,
                    "y": 387
                }
            ]
        },
        {
            "point": [
                {
                    "x": 139.44,
                    "y": 318.33
                },
                {
                    "x": 189.44,
                    "y": 368.33
                }
            ]
        },
        {
            "point": [
                {
                    "x": 163.44,
                    "y": 301.44
                },
                {
                    "x": 213.44,
                    "y": 351.44
                }
            ]
        }
    ]
}